pvv/__init__.py
pvv/exceptions.py
pvv-1.0.0.dist-info/LICENSE
pvv-1.0.0.dist-info/METADATA
pvv-1.0.0.dist-info/WHEEL
pvv-1.0.0.dist-info/RECORD
