Metadata-Version: 2.1
Name: pvv
Version: 1.0.0
Summary: Minimal Python decorator to enforce type validation from type hints
Home-page: https://github.com/mianfg/pvv
License: MIT
Keywords: typing,validator,decorator,validate
Author: mianfg
Author-email: hello@mianfg.me
Requires-Python: >=3.8,<4.0
Classifier: Development Status :: 5 - Production/Stable
Classifier: Intended Audience :: Developers
Classifier: Intended Audience :: Information Technology
Classifier: Intended Audience :: System Administrators
Classifier: License :: OSI Approved :: MIT License
Classifier: Programming Language :: Python
Classifier: Programming Language :: Python :: 3
Classifier: Programming Language :: Python :: 3.8
Classifier: Programming Language :: Python :: 3.9
Classifier: Programming Language :: Python :: 3.10
Classifier: Programming Language :: Python :: 3.11
Classifier: Programming Language :: Python :: 3.12
Classifier: Topic :: Software Development :: Libraries :: Python Modules
Project-URL: Documentation, https://github.com/mianfg/pvv/README.md
Project-URL: Repository, https://github.com/mianfg/pvv
